radie/__init__.py
radie/exceptions.py
radie/loaders.py
radie/util.py
radie/plugins/__init__.py
radie/plugins/examples/__init__.py
radie/plugins/examples/data/psd.csv
radie/plugins/examples/data/vsm.txt
radie/plugins/examples/data/xrd.ras
radie/plugins/loaders/__init__.py
radie/plugins/loaders/powderdiffraction_bruker_raw.py
radie/plugins/loaders/powderdiffraction_gsas.py
radie/plugins/loaders/powderdiffraction_peaks.py
radie/plugins/loaders/powderdiffraction_rigaku.py
radie/plugins/loaders/powderdiffraction_siemensD500.py
radie/plugins/loaders/psd_LA960.py
radie/plugins/loaders/ta_instruments.py
radie/plugins/loaders/vsm_lakeshore.py
radie/plugins/structures/__init__.py
radie/plugins/structures/dsc.py
radie/plugins/structures/powderdiffraction.py
radie/plugins/structures/psd.py
radie/plugins/structures/tga.py
radie/plugins/structures/vsm.py
radie/plugins/visualizations/__init__.py
radie/plugins/visualizations/powderdiffraction.py
radie/plugins/visualizations/psd.py
radie/plugins/visualizations/tga.py
radie/plugins/visualizations/icons/particlesizedistribution.svg
radie/plugins/visualizations/icons/powderdiffraction.svg
radie/plugins/visualizations/ui/__init__.py
radie/plugins/visualizations/ui/compile_all.py
radie/plugins/visualizations/ui/powderdiffraction.py
radie/plugins/visualizations/ui/psd.py
radie/plugins/visualizations/ui/tga.py
radie/qt/__init__.py
radie/qt/cfg.py
radie/qt/classes.py
radie/qt/colors.py
radie/qt/dataframeview.py
radie/qt/dpi.py
radie/qt/errors.py
radie/qt/excel_exporter.py
radie/qt/functions.py
radie/qt/indexabledict.py
radie/qt/masterdftree.py
radie/qt/plotlist.py
radie/qt/plotwidget.py
radie/qt/shortcuts.py
radie/qt/uchars.py
radie/qt/viewer.py
radie/qt/resources/icons/copyicon.svg
radie/qt/resources/icons/exiticon.svg
radie/qt/resources/icons/histogramicon.svg
radie/qt/resources/icons/pasteicon.svg
radie/qt/resources/icons/radie.svg
radie/qt/resources/icons/saveicon.svg
radie-0.1.4.dist-info/METADATA
radie-0.1.4.dist-info/RECORD
radie-0.1.4.dist-info/WHEEL
radie-0.1.4.dist-info/top_level.txt
