Metadata-Version: 2.1
Name: radie
Version: 0.1.4
Summary: a python application to rapidly import and view experimental data
Home-page: https://www.github.com/dvincentwest/radie
Author: D. Vincent West
Author-email: dvincentwest@gmail.com
License: GPLv2
Keywords: data visualization
Platform: UNKNOWN
Classifier: Development Status :: 3 - Alpha
Classifier: Intended Audience :: Science/Research
Classifier: License :: OSI Approved :: GNU General Public License v2 (GPLv2)
Classifier: Programming Language :: Python
Classifier: Topic :: Scientific/Engineering :: Visualization
Requires-Python: >=3.5
Requires-Dist: numpy
Requires-Dist: pandas
Requires-Dist: pyqtgraph
